vaes_ptorch/__init__.py
vaes_ptorch/args.py
vaes_ptorch/elbo.py
vaes_ptorch/train_vae.py
vaes_ptorch/utils.py
vaes_ptorch/vae.py
vaes_ptorch-0.0.dist-info/METADATA
vaes_ptorch-0.0.dist-info/WHEEL
vaes_ptorch-0.0.dist-info/top_level.txt
vaes_ptorch-0.0.dist-info/RECORD
